sonoff/__init__.py
sonoff/sonoff.py
sonoff_python-0.2.1.dist-info/LICENSE
sonoff_python-0.2.1.dist-info/METADATA
sonoff_python-0.2.1.dist-info/WHEEL
sonoff_python-0.2.1.dist-info/top_level.txt
sonoff_python-0.2.1.dist-info/RECORD
