Metadata-Version: 2.1
Name: sonoff-python
Version: 0.2.1
Summary: Make use of your sonoff smart switches without flashing them via the cloud APIs
Home-page: https://github.com/lucien2k/sonoff-python
Author: Alex Cowan
Author-email: acowan@gmail.com
License: MIT
Platform: UNKNOWN
Classifier: Programming Language :: Python :: 3
Classifier: License :: OSI Approved :: MIT License
Classifier: Operating System :: OS Independent
Requires-Dist: requests (>=2.12.4)
Requires-Dist: websocket-client (>=0.54.0)
